week10/ex2/ex2.v
module ex2 (x,y,cin,z,cout);
  input  x;
  input  y;
  input  cin;
  output z;
  output cout;
  wire w1;
  wire w2;
  wire w3;
  assign w1 = x ^ y;
  assign w2 = w1 & cin;
  assign w3 = x & y;
  assign z   = w1 ^ cin;
  assign cout = w2 | w3;
endmodule

week10/ex2/testbench.v
module testbench;

// input and output test signals
reg a, b, cin;
wire cout, sum;

// creating the instance of the module we want to test
ex2 fa(a, b, cin, sum, cout);
initial
begin
a = 1'b0;
b = 1'b1;
cin = 1'b0;
#5; // pause (5 units of delay )
cin = 1'b1;
#5;
a = 1'b1;
b = 1'b0;
#5;
cin = 1'b0;
#5
a = 1'b0;
b = 1'b0;
#5
cin = 1'b1;
#5
a = 1'b1;
b = 1'b1;
#5;
cin = 1'b0;
end

// print signal values on every change
initial
$monitor("a= %b b = %b cin = %b sum = %b cout = %b", a, b, cin, sum, cout);
initial
$dumpvars;
endmodule

week10/ex2/simulation/modelsim/dump.vcd
$date
	Thu Nov 05 21:18:01 2020
$end
$version
	ModelSim Version 10.5b
$end
$timescale
	1ps
$end

$scope module testbench $end
$var reg 1 ! a $end
$var reg 1 " b $end
$var reg 1 # cin $end
$var wire 1 $ cout $end
$var wire 1 % sum $end

$scope module fa $end
$var wire 1 & x $end
$var wire 1 ' y $end
$var wire 1 ( cin $end
$var wire 1 % z $end
$var wire 1 $ cout $end
$var wire 1 ) w1 $end
$var wire 1 * w2 $end
$var wire 1 + w3 $end
$upscope $end
$upscope $end
$enddefinitions $end
#0
$dumpvars
0!
1"
0#
0$
1%
1)
0*
0+
0(
1'
0&
$end
#5
1#
1(
1*
0%
1$
#10
1!
0"
1&
0'
#15
0#
0(
0*
1%
0$
#20
0!
0&
0)
0%
#25
1#
1(
1%
#30
1!
1"
1&
1'
1+
1$
#35
0#
0(
0%
